{
  "scan_id": "20260530-064537",
  "content_sha": "d7193a312c83404ed5ebebcf11ef873f190d26c0",
  "previous_sha": "c1265579903e261c397bef1405030f86ef68eeef",
  "detected_at": "2026-05-30T06:45:37.029965+00:00",
  "global_change": false,
  "state": "production",
  "staged_workflows": [
    {
      "workflow": "docs.aspose.org.yml",
      "staging_trigger_time": "2026-05-30T06:46:06Z",
      "staging_run_id": 26677237122,
      "staging_status": "success",
      "production_trigger_time": "2026-05-30T07:37:33Z",
      "production_run_id": null,
      "production_status": "triggered"
    },
    {
      "workflow": "kb.aspose.org.yml",
      "staging_trigger_time": "2026-05-30T06:46:13Z",
      "staging_run_id": 26677239029,
      "staging_status": "success",
      "production_trigger_time": "2026-05-30T07:37:39Z",
      "production_run_id": null,
      "production_status": "triggered"
    },
    {
      "workflow": "products.aspose.org.yml",
      "staging_trigger_time": "2026-05-30T06:46:19Z",
      "staging_run_id": 26677241178,
      "staging_status": "success",
      "production_trigger_time": "2026-05-30T07:37:45Z",
      "production_run_id": null,
      "production_status": "triggered"
    },
    {
      "workflow": "reference.aspose.org.yml",
      "staging_trigger_time": "2026-05-30T06:46:25Z",
      "staging_run_id": 26677243337,
      "staging_status": "success",
      "production_trigger_time": "2026-05-30T07:37:51Z",
      "production_run_id": null,
      "production_status": "triggered"
    }
  ],
  "production_only_workflows": [
    {
      "workflow": "blog.aspose.org.yml",
      "production_trigger_time": "2026-05-30T06:46:31Z",
      "production_run_id": 26677245275,
      "production_status": "success"
    }
  ],
  "completed_at": null,
  "failed_at": null,
  "error": null
}